aws_utils_lib/Functions.py
aws_utils_lib/__init__.py
aws_utils_lib-1.5.7.dist-info/METADATA
aws_utils_lib-1.5.7.dist-info/WHEEL
aws_utils_lib-1.5.7.dist-info/top_level.txt
aws_utils_lib-1.5.7.dist-info/RECORD
