Metadata-Version: 2.1
Name: aws-utils-lib
Version: 1.5.7
Summary: AWS utils library 
Home-page: https://github.com/swanm96
Author: Jonathan E. Aguiar
Author-email: jonathtanm@gmail.com
License: MIT
Requires-Dist: boto3
